sksdr/__init__.py
sksdr/agc.py
sksdr/channels.py
sksdr/coarse_freq_comp.py
sksdr/fec.py
sksdr/foo.py
sksdr/frame_sync.py
sksdr/freq_sync.py
sksdr/impairments.py
sksdr/interp_decim.py
sksdr/modulation.py
sksdr/phase_offset_est.py
sksdr/plotting.py
sksdr/psk_trans.py
sksdr/pulses.py
sksdr/scrambling.py
sksdr/sequences.py
sksdr/symbol_sync.py
sksdr/utils.py
scikit_sdr-0.2.dev0.dist-info/LICENSE
scikit_sdr-0.2.dev0.dist-info/METADATA
scikit_sdr-0.2.dev0.dist-info/WHEEL
scikit_sdr-0.2.dev0.dist-info/top_level.txt
scikit_sdr-0.2.dev0.dist-info/RECORD
