Metadata-Version: 2.1
Name: scikit-sdr
Version: 0.2.dev0
Summary: SDR scikit package
Home-page: https://github.com/dave-pi/scikit-sdr
Author: David Pi
Author-email: david.pinho@gmail.com
Maintainer: David Pi
Maintainer-email: david.pinho@gmail.com
License: MIT
Download-URL: https://github.com/dave-pi/scikit-sdr
Platform: UNKNOWN
Classifier: Development Status :: 1 - Planning
Classifier: Intended Audience :: Developers
Classifier: Intended Audience :: Science/Research
Classifier: License :: OSI Approved :: BSD License
Classifier: Topic :: Scientific/Engineering
Requires-Python: >=3.6
Requires-Dist: matplotlib
Requires-Dist: numpy
Requires-Dist: scipy
